sqlitefts/__init__.py
sqlitefts/__init__.pyi
sqlitefts/error.py
sqlitefts/error.pyi
sqlitefts/fts3.py
sqlitefts/fts3.pyi
sqlitefts/fts5.py
sqlitefts/fts5.pyi
sqlitefts/fts5_aux.py
sqlitefts/fts5_aux.pyi
sqlitefts/py.typed
sqlitefts/ranking.py
sqlitefts/ranking.pyi
sqlitefts/tokenizer.py
sqlitefts/tokenizer.pyi
sqlitefts-1.0.1.dist-info/METADATA
sqlitefts-1.0.1.dist-info/WHEEL
sqlitefts-1.0.1.dist-info/licenses/LICENSE
sqlitefts-1.0.1.dist-info/RECORD
