Metadata-Version: 2.4
Name: sqlitefts
Version: 1.0.1
Summary: A Python binding for tokenizers of SQLite Full Text Search
Project-URL: Homepage, https://github.com/hideaki-t/sqlite-fts-python/
Project-URL: Repository, https://github.com/hideaki-t/sqlite-fts-python.git
Author-email: Hideaki Takahashi <mymelo@gmail.com>
License: MIT
License-File: LICENSE
Keywords: FTS,FTS3,FTS4,FTS5,Full-text,SQLite,SQLite3,search
Classifier: Development Status :: 4 - Beta
Classifier: Intended Audience :: Developers
Classifier: License :: OSI Approved :: MIT License
Classifier: Operating System :: OS Independent
Classifier: Programming Language :: Python :: 2.7
Classifier: Programming Language :: Python :: 3.10
Classifier: Programming Language :: Python :: 3.11
Classifier: Programming Language :: Python :: 3.12
Classifier: Programming Language :: Python :: 3.13
Classifier: Programming Language :: Python :: 3.14
Classifier: Programming Language :: Python :: Implementation :: CPython
Classifier: Programming Language :: Python :: Implementation :: PyPy
Classifier: Topic :: Database
Classifier: Topic :: Software Development :: Libraries :: Python Modules
Requires-Python: !=3.0,!=3.1,!=3.2,!=3.3,!=3.4,!=3.5,!=3.6,!=3.7,!=3.8,>=2.7
Requires-Dist: cffi>=1.15.1; platform_python_implementation != 'PyPy'
Requires-Dist: cffi>=1.17.0; python_version >= '3.9'
Requires-Dist: cffi>=2.0.0; python_version >= '3.14'
